content/forms.py
content/urls.py
content/models.py
content/views.py
content/__init__.py
content/admin.py
django_content_toolkit-0.1.3.dist-info/WHEEL
django_content_toolkit-0.1.3.dist-info/DESCRIPTION.rst
django_content_toolkit-0.1.3.dist-info/METADATA
django_content_toolkit-0.1.3.dist-info/metadata.json
django_content_toolkit-0.1.3.dist-info/top_level.txt
django_content_toolkit-0.1.3.dist-info/RECORD
