Metadata-Version: 2.0
Name: django-content-toolkit
Version: 0.1.3
Summary: A simple Django package for model translations
Home-page: https://github.com/esistgut/django-content-toolkit
Author: Giacomo Graziosi
Author-email: g.graziosi@gmail.com
License: MIT
Platform: UNKNOWN
Classifier: Environment :: Web Environment
Classifier: Framework :: Django
Classifier: Intended Audience :: Developers
Classifier: Operating System :: OS Independent
Classifier: Programming Language :: Python
Classifier: Programming Language :: Python :: 3
Classifier: Programming Language :: Python :: 3.4
Classifier: Topic :: Internet :: WWW/HTTP
Classifier: Topic :: Internet :: WWW/HTTP :: Dynamic Content
Requires-Dist: Django
Requires-Dist: django-polymorphic
Requires-Dist: django-reversion
Requires-Dist: django-mptt
Requires-Dist: django-taggit
